AUTHORS.txt
LICENSE.txt
MANIFEST.in
README.md
setup.py
django_servee.egg-info/PKG-INFO
django_servee.egg-info/SOURCES.txt
django_servee.egg-info/dependency_links.txt
django_servee.egg-info/not-zip-safe
django_servee.egg-info/requires.txt
django_servee.egg-info/top_level.txt
docs/1.2_considerations.txt
docs/Makefile
docs/conf.py
docs/index.txt
docs/inlines.txt
docs/installation.txt
docs/intro.txt
docs/make.bat
docs/sample_projects.txt
docs/wysiwyg.txt
servee/.DS_Store
servee/.gitignore
servee/__init__.py
servee/__init__.pyc
servee/utils.py
servee/utils.pyc
servee/frontendadmin/.DS_Store
servee/frontendadmin/__init__.py
servee/frontendadmin/__init__.pyc
servee/frontendadmin/forms.py
servee/frontendadmin/forms.pyc
servee/frontendadmin/insert.py
servee/frontendadmin/insert.pyc
servee/frontendadmin/models.py
servee/frontendadmin/models.pyc
servee/frontendadmin/options.py
servee/frontendadmin/options.pyc
servee/frontendadmin/sites.py
servee/frontendadmin/sites.pyc
servee/frontendadmin/static/.DS_Store
servee/frontendadmin/static/servee/.DS_Store
servee/frontendadmin/static/servee/css/admin.css
servee/frontendadmin/static/servee/css/animate.css
servee/frontendadmin/static/servee/css/formOverrides.css
servee/frontendadmin/static/servee/css/inline-type-forms.css
servee/frontendadmin/static/servee/css/overlay-type-forms.css
servee/frontendadmin/static/servee/css/overlay.css
servee/frontendadmin/static/servee/images/buttonBG.png
servee/frontendadmin/static/servee/images/doc-icon.png
servee/frontendadmin/static/servee/images/gallery-icon.png
servee/frontendadmin/static/servee/images/imageIcon.png
servee/frontendadmin/static/servee/images/small-icons.png
servee/frontendadmin/static/servee/images/srv-icons.png
servee/frontendadmin/static/servee/js/frontendadmin.js
servee/frontendadmin/templates/servee/404.html
servee/frontendadmin/templates/servee/500.html
servee/frontendadmin/templates/servee/_search_form.html
servee/frontendadmin/templates/servee/_submit_line.html
servee/frontendadmin/templates/servee/actions.html
servee/frontendadmin/templates/servee/app_index.html
servee/frontendadmin/templates/servee/base.html
servee/frontendadmin/templates/servee/base_site.html
