Metadata-Version: 1.0
Name: django-servee
Version: 0.7a1.dev1
Summary: Inline Wysiwyg editing making use of a subclassed Django Admin
Home-page: http://github.com/servee/servee/
Author: Issac Kelly
Author-email: issac@servee.com
License: BSD
Platform: UNKNOWN
Classifier: Development Status :: 3 - Alpha
Classifier: Framework :: Django
Classifier: Intended Audience :: Developers
Classifier: License :: OSI Approved :: BSD License
Classifier: Operating System :: OS Independent
Classifier: Programming Language :: Python
Classifier: Topic :: Internet :: WWW/HTTP
